pytest_is_running/__init__.py
pytest_is_running/plugin.py
pytest_is_running/py.typed
pytest_is_running-1.5.1.dist-info/LICENSE
pytest_is_running-1.5.1.dist-info/METADATA
pytest_is_running-1.5.1.dist-info/WHEEL
pytest_is_running-1.5.1.dist-info/entry_points.txt
pytest_is_running-1.5.1.dist-info/top_level.txt
pytest_is_running-1.5.1.dist-info/RECORD
