Metadata-Version: 2.1
Name: pytest-is-running
Version: 1.5.1
Summary: pytest plugin providing a function to check if pytest is running.
Author-email: Adam Johnson <me@adamj.eu>
License: MIT
Project-URL: Changelog, https://github.com/adamchainz/pytest-is-running/blob/main/CHANGELOG.rst
Project-URL: Funding, https://adamj.eu/books/
Project-URL: Repository, https://github.com/adamchainz/pytest-is-running
Keywords: pytest
Classifier: Development Status :: 7 - Inactive
Classifier: Framework :: Pytest
Classifier: Intended Audience :: Developers
Classifier: License :: OSI Approved :: MIT License
Classifier: Natural Language :: English
Classifier: Programming Language :: Python :: 3 :: Only
Classifier: Programming Language :: Python :: 3.8
Classifier: Programming Language :: Python :: 3.9
Classifier: Programming Language :: Python :: 3.10
Classifier: Programming Language :: Python :: 3.11
Classifier: Programming Language :: Python :: 3.12
Classifier: Typing :: Typed
Requires-Python: >=3.8
License-File: LICENSE
